bhfutils/__init__.py
bhfutils/crawler/__init__.py
bhfutils/crawler/bhf_signals.py
bhfutils/crawler/custom_cookies.py
bhfutils/crawler/distributed_scheduler.py
bhfutils/crawler/expire.py
bhfutils/crawler/items.py
bhfutils/crawler/log_retry_middleware.py
bhfutils/crawler/meta_passthrough_middleware.py
bhfutils/crawler/pipelines.py
bhfutils/crawler/policy.py
bhfutils/crawler/proxy_rotate.py
bhfutils/crawler/redis_domain_max_page_filter.py
bhfutils/crawler/redis_dupefilter.py
bhfutils/crawler/redis_global_page_per_domain_filter.py
bhfutils/crawler/redis_retry_middleware.py
bhfutils/crawler/redis_stats_middleware.py
bhfutils/crawler/settings_template.py
bhfutils/crawler/config/__init__.py
bhfutils/crawler/config/file_pusher.py
bhfutils/crawler/playwright/__init__.py
bhfutils/crawler/playwright/handler.py
bhfutils/crawler/playwright/headers.py
bhfutils/crawler/playwright/page.py
bhfutils/crawler/playwright/stealth.py
bhfutils/crawler/playwright/cursor/__init__.py
bhfutils/crawler/playwright/cursor/do_async/__init__.py
bhfutils/crawler/playwright/cursor/do_async/_mouse_helper.py
bhfutils/crawler/playwright/cursor/do_async/_spoof.py
bhfutils/crawler/playwright/cursor/do_sync/__init__.py
bhfutils/crawler/playwright/cursor/do_sync/_mouse_helper.py
bhfutils/crawler/playwright/cursor/do_sync/_spoof.py
bhfutils/crawler/playwright/cursor/js/mouseHelper.js
bhfutils/crawler/playwright/cursor/shared/__init__.py
bhfutils/crawler/playwright/cursor/shared/math.py
bhfutils/crawler/playwright/cursor/shared/spoof.py
bhfutils/crawler/playwright/js/__init__.py
bhfutils/crawler/playwright/js/chrome.app.js
bhfutils/crawler/playwright/js/chrome.csi.js
bhfutils/crawler/playwright/js/chrome.loadtimes.js
bhfutils/crawler/playwright/js/chrome.runtime.js
bhfutils/crawler/playwright/js/hairline.js
bhfutils/crawler/playwright/js/iframe.contentWindow.js
bhfutils/crawler/playwright/js/magic-arrays.js
bhfutils/crawler/playwright/js/media.codecs.js
bhfutils-0.2.99.dist-info/METADATA
bhfutils-0.2.99.dist-info/WHEEL
bhfutils-0.2.99.dist-info/top_level.txt
bhfutils-0.2.99.dist-info/zip-safe
bhfutils-0.2.99.dist-info/RECORD
