Metadata-Version: 2.4
Name: bhfutils
Version: 0.2.99
Summary: Utilities that are used by any spider of Behoof project
Home-page: https://behoof.app/
Author: Teplygin Vladimir
Author-email: vvteplygin@gmail.com
License: MIT
Keywords: behoof,scrapy-cluster,utilities
Requires-Dist: python-json-logger==0.1.8
Requires-Dist: redis>=4.0.2
Requires-Dist: kazoo>=2.8.0
Requires-Dist: mock>=4.0.3
Requires-Dist: playwright>=1.17.2
Requires-Dist: testfixtures>=6.18.3
Requires-Dist: ujson>=4.3.0
Requires-Dist: future>=0.18.2
Provides-Extra: test
Requires-Dist: mock>=2.0.0; extra == "test"
Requires-Dist: testfixtures>=4.13.5; extra == "test"
Provides-Extra: all
Requires-Dist: python-json-logger==0.1.8; extra == "all"
Requires-Dist: redis>=4.0.2; extra == "all"
Requires-Dist: kazoo>=2.8.0; extra == "all"
Requires-Dist: mock>=4.0.3; extra == "all"
Requires-Dist: playwright>=1.17.2; extra == "all"
Requires-Dist: testfixtures>=6.18.3; extra == "all"
Requires-Dist: ujson>=4.3.0; extra == "all"
Requires-Dist: future>=0.18.2; extra == "all"
Requires-Dist: mock>=2.0.0; extra == "all"
Requires-Dist: testfixtures>=4.13.5; extra == "all"
Provides-Extra: docs
Requires-Dist: sphinx; extra == "docs"
Requires-Dist: mock>=2.0.0; extra == "docs"
Requires-Dist: testfixtures>=4.13.5; extra == "docs"
Provides-Extra: lint
Requires-Dist: pep8; extra == "lint"
Requires-Dist: pyflakes; extra == "lint"
Dynamic: author
Dynamic: author-email
Dynamic: description
Dynamic: description-content-type
Dynamic: home-page
Dynamic: keywords
Dynamic: license
Dynamic: provides-extra
Dynamic: requires-dist
Dynamic: summary
